barkion.py
barkion-1.0.1.dist-info/METADATA
barkion-1.0.1.dist-info/WHEEL
barkion-1.0.1.dist-info/top_level.txt
barkion-1.0.1.dist-info/RECORD
