Metadata-Version: 2.1
Name: barkion
Version: 1.0.1
Summary: Snippets of DataScience: Pandas and dataViz
Home-page: UNKNOWN
Author: Rafael Morais de Assis
License: UNKNOWN
Platform: UNKNOWN
Classifier: Programming Language :: Python :: 3
Classifier: License :: OSI Approved :: MIT License
Classifier: Operating System :: OS Independent
Requires-Python: >=3.6
Requires-Dist: pandas
